MercyStudy/__init__.py
MercyStudy/code_convert.py
MercyStudy/dec_convert.py
MercyStudy/get_num.py
MercyStudy/mercy_decorators.py
MercyStudy/mercy_math.py
MercyIdeas-1.0.0a2.dist-info/LICENSE.txt
MercyIdeas-1.0.0a2.dist-info/METADATA
MercyIdeas-1.0.0a2.dist-info/WHEEL
MercyIdeas-1.0.0a2.dist-info/top_level.txt
MercyIdeas-1.0.0a2.dist-info/RECORD
