Metadata-Version: 2.1
Name: MercyIdeas
Version: 1.0.0a2
Summary: UNKNOWN
Home-page: https://github.com/MercyNaima/PythonStudy
Author: MercyNaima
Author-email: 2868681725@qq.com
License: UNKNOWN
Platform: UNKNOWN
Classifier: Programming Language :: Python :: 3.9
Classifier: License :: OSI Approved :: MIT License
Classifier: Operating System :: OS Independent
License-File: LICENSE.txt
